{
  "sections": [
    {
      "title": "Getting Started",
      "items": [
        {"title": "Introduction", "url": "/", "file": "index"},
        {"title": "Installation", "url": "/installation/", "file": "installation"}
      ]
    },
    {
      "title": "Core Features",
      "items": [
        {"title": "Loading PSDs", "url": "/posts/loading/", "file": "posts/loading"},
        {"title": "Placing Layers", "url": "/posts/placing/", "file": "posts/placing"},
        {"title": "Sprite Types", "url": "/posts/sprite-types/", "file": "posts/sprite-types"}
      ]
    },
    {
      "title": "Advanced Features",
      "items": [
        {"title": "Cameras", "url": "/cameras/", "file": "cameras"},
        {"title": "LazyLoad", "url": "/cameras/lazyload/", "file": "cameras/lazyload"},
        {"title": "Draggable Camera", "url": "/cameras/draggable/", "file": "cameras/draggable"}
      ]
    },
    {
      "title": "Presets",
      "items": [
        {"title": "Overview", "url": "/presets/", "file": "presets"},
        {"title": "Button", "url": "/presets/button/", "file": "presets/button"},
        {"title": "Parallax", "url": "/presets/parallax/", "file": "presets/parallax"},
        {"title": "Pan To", "url": "/presets/panto/", "file": "presets/panto"},
        {"title": "Fill Zone", "url": "/presets/fillzone/", "file": "presets/fillzone"},
        {"title": "Joystick", "url": "/presets/joystick/", "file": "presets/joystick"}
      ]
    }
  ]
}